algomancy_utils/__init__.py
algomancy_utils/baseparameterset.py
algomancy_utils/logger.py
algomancy_utils/py.typed
algomancy_utils/unit.py
algomancy_utils-0.3.18.dist-info/WHEEL
algomancy_utils-0.3.18.dist-info/METADATA
algomancy_utils-0.3.18.dist-info/RECORD
