Metadata-Version: 2.3
Name: algomancy-utils
Version: 0.3.18
Summary: Miscellaneous modules used in the Algomancy library
Author: Pepijn Wissing
Author-email: Pepijn Wissing <Wsg@cqm.nl>
Requires-Dist: strenum>=0.4.15
Requires-Python: >=3.14
